gemini/AI.py
gemini/__init__.py
GeminiRequests-1.0.9.dist-info/METADATA
GeminiRequests-1.0.9.dist-info/WHEEL
GeminiRequests-1.0.9.dist-info/top_level.txt
GeminiRequests-1.0.9.dist-info/RECORD
