Metadata-Version: 2.1
Name: GeminiRequests
Version: 1.0.9
Summary: An example Python package
Author: Promiteus
Author-email: sbdt.israel@gmail.com
License: MIT
Requires-Dist: requests
